asyncmq/__init__.py
asyncmq/__main__.py
asyncmq/exceptions.py
asyncmq/flow.py
asyncmq/jobs.py
asyncmq/logging.py
asyncmq/monkay.py
asyncmq/py.typed
asyncmq/queues.py
asyncmq/rate_limiter.py
asyncmq/runners.py
asyncmq/sandbox.py
asyncmq/schedulers.py
asyncmq/tasks.py
asyncmq/workers.py
asyncmq/backends/__init__.py
asyncmq/backends/base.py
asyncmq/backends/memory.py
asyncmq/backends/mongodb.py
asyncmq/backends/postgres.py
asyncmq/backends/rabbitmq.py
asyncmq/backends/redis.py
asyncmq/cli/__init__.py
asyncmq/cli/__main__.py
asyncmq/cli/info.py
asyncmq/cli/job.py
asyncmq/cli/queue.py
asyncmq/cli/utils.py
asyncmq/cli/worker.py
asyncmq/cli/helpers/__init__.py
asyncmq/cli/helpers/env.py
asyncmq/cli/helpers/groups.py
asyncmq/conf/__init__.py
asyncmq/conf/global_settings.py
asyncmq/contrib/__init__.py
asyncmq/contrib/dashboard/__init__.py
asyncmq/contrib/dashboard/application.py
asyncmq/contrib/dashboard/engine.py
asyncmq/contrib/dashboard/messages.py
asyncmq/contrib/dashboard/mixins.py
asyncmq/contrib/dashboard/utils.py
asyncmq/contrib/dashboard/admin/__init__.py
asyncmq/contrib/dashboard/admin/core.py
asyncmq/contrib/dashboard/admin/middleware.py
asyncmq/contrib/dashboard/admin/protocols.py
asyncmq/contrib/dashboard/admin/backends/__init__.py
asyncmq/contrib/dashboard/admin/backends/jwt.py
asyncmq/contrib/dashboard/admin/backends/simple_user.py
asyncmq/contrib/dashboard/controllers/__init__.py
asyncmq/contrib/dashboard/controllers/dlq.py
asyncmq/contrib/dashboard/controllers/home.py
asyncmq/contrib/dashboard/controllers/jobs.py
asyncmq/contrib/dashboard/controllers/metrics.py
asyncmq/contrib/dashboard/controllers/queues.py
asyncmq/contrib/dashboard/controllers/repeatables.py
asyncmq/contrib/dashboard/controllers/sse.py
asyncmq/contrib/dashboard/controllers/workers.py
asyncmq/contrib/dashboard/statics/css/asyncmq.css
asyncmq/contrib/dashboard/statics/css/toastify.min.css
asyncmq/contrib/dashboard/statics/js/asyncmq.js
asyncmq/contrib/dashboard/statics/js/toastify.min.js
asyncmq-0.6.2.dist-info/METADATA
asyncmq-0.6.2.dist-info/WHEEL
asyncmq-0.6.2.dist-info/entry_points.txt
asyncmq-0.6.2.dist-info/licenses/LICENSE
asyncmq-0.6.2.dist-info/RECORD
