Metadata-Version: 2.4
Name: asyncmq
Version: 0.6.2
Summary: Async task queue with BullMQ-like features
Project-URL: Homepage, https://github.com/dymmond/asyncmq
Project-URL: Documentation, https://asyncmq.dymmond.com
Project-URL: Changelog, https://asyncmq.dymmond.com/release-notes/
Project-URL: Funding, https://github.com/sponsors/tarsil
Project-URL: Source, https://github.com/dymmond/asyncmq
Author-email: Tiago Silva <tiago@tarsild.io>
License-File: LICENSE
Keywords: anyio,asyncio,background-jobs,celery-alternative,concurrency,cron,dead-letter-queue,esmerald,fastapi,job-scheduler,microservices,mongodb,parallelism,postgresql,rate-limiter,ravyn,redis,retry-policy,task-queue
Classifier: Development Status :: 4 - Beta
Classifier: Environment :: Web Environment
Classifier: Framework :: AnyIO
Classifier: Framework :: AsyncIO
Classifier: Intended Audience :: Developers
Classifier: Intended Audience :: Information Technology
Classifier: Intended Audience :: System Administrators
Classifier: License :: OSI Approved :: BSD License
Classifier: Operating System :: OS Independent
Classifier: Programming Language :: Python
Classifier: Programming Language :: Python :: 3
Classifier: Programming Language :: Python :: 3 :: Only
Classifier: Programming Language :: Python :: 3.10
Classifier: Programming Language :: Python :: 3.11
Classifier: Programming Language :: Python :: 3.12
Classifier: Programming Language :: Python :: 3.13
Classifier: Programming Language :: Python :: 3.14
Classifier: Topic :: Internet
Classifier: Topic :: Internet :: WWW/HTTP
Classifier: Topic :: Internet :: WWW/HTTP :: HTTP Servers
Classifier: Topic :: Software Development
Classifier: Topic :: Software Development :: Libraries
Classifier: Topic :: Software Development :: Libraries :: Application Frameworks
Classifier: Topic :: Software Development :: Libraries :: Python Modules
Classifier: Typing :: Typed
Requires-Python: >=3.10
Requires-Dist: croniter<7.0.0,>=6.0.0
Requires-Dist: lilya[standard]>=0.22.15
Requires-Dist: redis>=7.0.0
Provides-Extra: aio-pika
Requires-Dist: aio-pika>=9.5.8; extra == 'aio-pika'
Provides-Extra: all
Requires-Dist: aio-pika; extra == 'all'
Requires-Dist: mongo; extra == 'all'
Requires-Dist: postgres; extra == 'all'
Provides-Extra: mongo
Requires-Dist: motor>=3.7.0; extra == 'mongo'
Provides-Extra: postgres
Requires-Dist: asyncpg>=0.30.0; extra == 'postgres'
Provides-Extra: testing
Requires-Dist: aio-pika>=9.5.5; extra == 'testing'
Requires-Dist: anyio[trio]<6.0.0,>=4.9.0; extra == 'testing'
Requires-Dist: autoflake<3.0.0,>=2.0.2; extra == 'testing'
Requires-Dist: black<25.0,==24.1.1; extra == 'testing'
Requires-Dist: fastapi; extra == 'testing'
Requires-Dist: httpx; extra == 'testing'
Requires-Dist: ipdb; extra == 'testing'
Requires-Dist: isort<6.0.0,>=5.12.0; extra == 'testing'
Requires-Dist: pyjwt; extra == 'testing'
Requires-Dist: pytest-asyncio>=0.26.0; extra == 'testing'
Requires-Dist: pytest-cov<5.0.0,>=4.0.0; extra == 'testing'
Requires-Dist: pytest<9.0.0,>=7.2.2; extra == 'testing'
Requires-Dist: ravyn>=0.3.2; extra == 'testing'
Requires-Dist: structlog>=25.3.0; extra == 'testing'
Requires-Dist: uvicorn>=0.34.2; extra == 'testing'
